htmlgraph/__init__.py
htmlgraph/__init__.pyi
htmlgraph/agent_detection.py
htmlgraph/agent_registry.py
htmlgraph/agents.py
htmlgraph/analytics_index.py
htmlgraph/atomic_ops.py
htmlgraph/attribute_index.py
htmlgraph/cli_framework.py
htmlgraph/config.py
htmlgraph/context_analytics.py
htmlgraph/converter.py
htmlgraph/dashboard.html
htmlgraph/dashboard.html.backup
htmlgraph/dashboard.html.bak
htmlgraph/dashboard.html.bak2
htmlgraph/dashboard.html.bak3
htmlgraph/decorators.py
htmlgraph/dependency_models.py
htmlgraph/deploy.py
htmlgraph/deployment_models.py
htmlgraph/edge_index.py
htmlgraph/error_handler.py
htmlgraph/event_log.py
htmlgraph/event_migration.py
htmlgraph/exceptions.py
htmlgraph/file_watcher.py
htmlgraph/find_api.py
htmlgraph/git_events.py
htmlgraph/graph.py
htmlgraph/ids.py
htmlgraph/index.d.ts
htmlgraph/learning.py
htmlgraph/mcp_server.py
htmlgraph/models.py
htmlgraph/orchestration.md
htmlgraph/orchestrator-system-prompt-optimized.txt
htmlgraph/orchestrator.py
htmlgraph/orchestrator_config.py
htmlgraph/orchestrator_mode.py
htmlgraph/orchestrator_validator.py
htmlgraph/parallel.py
htmlgraph/parser.py
htmlgraph/planning.py
htmlgraph/pydantic_models.py
htmlgraph/quality_gates.py
htmlgraph/query_builder.py
htmlgraph/reflection.py
htmlgraph/refs.py
htmlgraph/repo_hash.py
htmlgraph/routing.py
htmlgraph/server.py
htmlgraph/session_hooks.py
htmlgraph/session_manager.py
htmlgraph/session_registry.py
htmlgraph/session_state.py
htmlgraph/session_warning.py
htmlgraph/setup.py
htmlgraph/spike_index.py
htmlgraph/styles.css
htmlgraph/sync_docs.py
htmlgraph/system_prompts.py
htmlgraph/track_builder.py
htmlgraph/track_manager.py
htmlgraph/transcript.py
htmlgraph/transcript_analytics.py
htmlgraph/types.py
htmlgraph/validation.py
htmlgraph/watch.py
htmlgraph/work_type_utils.py
htmlgraph/.htmlgraph/.session-warning-state.json
htmlgraph/.htmlgraph/agents.json
htmlgraph/.htmlgraph/htmlgraph.db
htmlgraph/analytics/__init__.py
htmlgraph/analytics/cli.py
htmlgraph-0.27.2.dist-info/METADATA
htmlgraph-0.27.2.dist-info/WHEEL
htmlgraph-0.27.2.dist-info/entry_points.txt
htmlgraph-0.27.2.dist-info/RECORD
