Metadata-Version: 2.4
Name: htmlgraph
Version: 0.27.2
Summary: HTML is All You Need - Graph database on web standards
Project-URL: Homepage, https://github.com/Shakes-tzd/htmlgraph
Project-URL: Documentation, https://github.com/Shakes-tzd/htmlgraph#readme
Project-URL: Repository, https://github.com/Shakes-tzd/htmlgraph
Project-URL: Issues, https://github.com/Shakes-tzd/htmlgraph/issues
Author-email: Shakes <shakestzd@gmail.com>
License: MIT
Keywords: agents,ai,css,database,graph,html
Classifier: Development Status :: 3 - Alpha
Classifier: Intended Audience :: Developers
Classifier: License :: OSI Approved :: MIT License
Classifier: Programming Language :: Python :: 3
Classifier: Programming Language :: Python :: 3.10
Classifier: Programming Language :: Python :: 3.11
Classifier: Programming Language :: Python :: 3.12
Classifier: Topic :: Database
Classifier: Topic :: Software Development :: Libraries :: Python Modules
Requires-Python: >=3.10
Requires-Dist: aiosqlite>=0.19.0
Requires-Dist: fastapi>=0.104.0
Requires-Dist: jinja2>=3.1.0
Requires-Dist: justhtml>=0.6.0
Requires-Dist: pydantic>=2.0.0
Requires-Dist: rich>=13.0.0
Requires-Dist: typing-extensions>=4.0.0; python_version < '3.11'
Requires-Dist: uvicorn>=0.24.0
Requires-Dist: watchdog>=3.0.0
Provides-Extra: deploy
Requires-Dist: invoke>=2.2.0; extra == 'deploy'
Provides-Extra: dev
Requires-Dist: black>=23.0.0; extra == 'dev'
Requires-Dist: invoke>=2.2.0; extra == 'dev'
Requires-Dist: mypy>=1.0.0; extra == 'dev'
Requires-Dist: pdoc>=14.0.0; extra == 'dev'
Requires-Dist: pytest-asyncio>=0.23.0; extra == 'dev'
Requires-Dist: pytest-cov>=4.0.0; extra == 'dev'
Requires-Dist: pytest>=7.0.0; extra == 'dev'
Requires-Dist: pyyaml>=6.0; extra == 'dev'
Requires-Dist: ruff>=0.1.0; extra == 'dev'
Requires-Dist: tomli>=2.0.0; (python_version < '3.11') and extra == 'dev'
Provides-Extra: sqlite
Requires-Dist: aiosqlite>=0.19.0; extra == 'sqlite'
